yoggopoth/__init__.py
yoggopoth/__main__.py
yoggopoth/api.py
yoggopoth/models.py
yoggopoth/settings.py
yoggopoth/trainer.py
yoggopoth-0.0.2.dist-info/LICENSE
yoggopoth-0.0.2.dist-info/METADATA
yoggopoth-0.0.2.dist-info/WHEEL
yoggopoth-0.0.2.dist-info/top_level.txt
yoggopoth-0.0.2.dist-info/RECORD
