Metadata-Version: 2.1
Name: yoggopoth
Version: 0.0.2
Summary: YogGoPoTh: learning Transformers with the Cthulhu Mythos!
Author-email: Artem Gorokhov <branntart@gmail.com>
Project-URL: Homepage, https://github.com/brannt/yoggopoth
Project-URL: Issues, https://github.com/brannt/yoggopoth/issues
Classifier: Programming Language :: Python :: 3
Classifier: Programming Language :: Python :: 3.10
Classifier: License :: OSI Approved :: MIT License
Classifier: Operating System :: OS Independent
Requires-Python: >=3.10
License-File: LICENSE
Requires-Dist: torch ~=2.2.0
Requires-Dist: fire ~=0.6.0
Requires-Dist: pydantic-settings ~=2.2.1
Requires-Dist: numpy ~=1.26.4
Provides-Extra: dev
Requires-Dist: ruff ; extra == 'dev'
Requires-Dist: build ; extra == 'dev'
Requires-Dist: twine ; extra == 'dev'
